mvits/__init__.py
mvits/predict.py
mvits/trainer.py
mvits/data_utils/__init__.py
mvits/data_utils/collate_fn.py
mvits/data_utils/mel_processing.py
mvits/data_utils/reader.py
mvits/data_utils/sampler.py
mvits/models/__init__.py
mvits/models/attentions.py
mvits/models/commons.py
mvits/models/losses.py
mvits/models/models.py
mvits/models/modules.py
mvits/models/transforms.py
mvits/text/__init__.py
mvits/text/cantonese.py
mvits/text/cleaners.py
mvits/text/english.py
mvits/text/japanese.py
mvits/text/korean.py
mvits/text/mandarin.py
mvits/text/ngu_dialect.py
mvits/text/shanghainese.py
mvits/text/symbol.py
mvits/text/chinese_dialect_lexicons/README.md
mvits/text/chinese_dialect_lexicons/changzhou.json
mvits/text/chinese_dialect_lexicons/changzhou.ocd2
mvits/text/chinese_dialect_lexicons/changzhou_3.json
mvits/text/chinese_dialect_lexicons/changzhou_3.ocd2
mvits/text/chinese_dialect_lexicons/cixi_2.json
mvits/text/chinese_dialect_lexicons/cixi_2.ocd2
mvits/text/chinese_dialect_lexicons/fuyang_2.json
mvits/text/chinese_dialect_lexicons/fuyang_2.ocd2
mvits/text/chinese_dialect_lexicons/hangzhou_2.json
mvits/text/chinese_dialect_lexicons/hangzhou_2.ocd2
mvits/text/chinese_dialect_lexicons/jiading_2.json
mvits/text/chinese_dialect_lexicons/jiading_2.ocd2
mvits/text/chinese_dialect_lexicons/jiashan_2.json
mvits/text/chinese_dialect_lexicons/jiashan_2.ocd2
mvits/text/chinese_dialect_lexicons/jingjiang_2.json
mvits/text/chinese_dialect_lexicons/jingjiang_2.ocd2
mvits/text/chinese_dialect_lexicons/jyutjyu_2.json
mvits/text/chinese_dialect_lexicons/jyutjyu_2.ocd2
mvits/text/chinese_dialect_lexicons/linping_2.json
mvits/text/chinese_dialect_lexicons/linping_2.ocd2
mvits/text/chinese_dialect_lexicons/ningbo_2.json
mvits/text/chinese_dialect_lexicons/ningbo_2.ocd2
mvits/text/chinese_dialect_lexicons/pinghu_2.json
mvits/text/chinese_dialect_lexicons/pinghu_2.ocd2
mvits/text/chinese_dialect_lexicons/ruao_2.json
mvits/text/chinese_dialect_lexicons/ruao_2.ocd2
mvits-0.0.4.dist-info/LICENSE
mvits-0.0.4.dist-info/METADATA
mvits-0.0.4.dist-info/WHEEL
mvits-0.0.4.dist-info/top_level.txt
mvits-0.0.4.dist-info/RECORD
