Metadata-Version: 2.1
Name: mvits
Version: 0.0.4
Summary: VITS toolkit on Pytorch
Home-page: https://github.com/yeyupiaoling/VITS-Pytorch
Author: yeyupiaoling
License: Apache License 2.0
Download-URL: https://github.com/yeyupiaoling/VITS-Pytorch.git
Keywords: audio,pytorch,tts
Platform: UNKNOWN
Classifier: Intended Audience :: Developers
Classifier: License :: OSI Approved :: Apache Software License
Classifier: Operating System :: OS Independent
Classifier: Natural Language :: Chinese (Simplified)
Classifier: Programming Language :: Python :: 3
Classifier: Programming Language :: Python :: 3.5
Classifier: Programming Language :: Python :: 3.6
Classifier: Programming Language :: Python :: 3.7
Classifier: Programming Language :: Python :: 3.8
Classifier: Programming Language :: Python :: 3.9
Classifier: Topic :: Utilities
License-File: LICENSE
Requires-Dist: jamo (>=0.4.1)
Requires-Dist: inflect (>=7.0.0)
Requires-Dist: unidecode (>=1.3.6)
Requires-Dist: pyopenjtalk (>=0.3.1)
Requires-Dist: jieba (>=0.42.1)
Requires-Dist: pypinyin (>=0.49.0)
Requires-Dist: termcolor (>=1.1.0)
Requires-Dist: numpy (>=1.23.5)
Requires-Dist: scikit-learn (>=1.1.1)
Requires-Dist: torchinfo (>=1.8.0)
Requires-Dist: tqdm (>=4.65.0)
Requires-Dist: visualdl (>=2.5.3)
Requires-Dist: torchaudio (>=0.13.0)
Requires-Dist: librosa (>=0.10.1)
Requires-Dist: matplotlib (==3.3.1)
Requires-Dist: soundfile (>=0.12.1)
Requires-Dist: pyyaml (>=5.4.1)
Requires-Dist: cn2an (>=0.5.22)
Requires-Dist: monotonic-align
Requires-Dist: eng-to-ipa
Requires-Dist: ko-pron
Requires-Dist: phonemizer
Requires-Dist: indic-transliteration
Requires-Dist: num-thai
Requires-Dist: opencc
